[
    {
        "review_text": "Recomendada, es una excelente herramienta, gracias a la publicación supe el lugar donde se encontraba mi mascota Mateo",
        "review_date": 1574214553,
        "review_display_date": "2019-11-20T01:49:13+0000",
        "review_length": 118,
        "reviewer_name": "Mario Arley Villamizar",
        "reviewer_country": "Colombia.png",
        "review_link": "https://www.facebook.com/yelra.villamizar/posts/1935066863293326",
        "reviewer_picture": "mario_mateo.jpg",
        "display_date": "19/11/2019"
    },
    {
        "review_text": "Excelente servicio y sobre todo me encantó la atención brindada en todo momento. Estuvieron pedientes de cualquier noticia. La pérdida de una mascota es lo peor que uno puede sentir, es un momento que no le deseo a nadie, sé que el post llegó adonde tenía que llegar, por eso hoy está mi princesa ya conmigo en casa tranquila y descansando ¡mil gracias por todo! Recomiendo al 100 Clabki 😍😍",
        "review_date": 1574183429,
        "review_display_date": "2019-11-19T17:10:29+0000",
        "review_length": 397,
        "reviewer_name": "Itzel De Landazuri",
        "reviewer_country": "Mexico.png",
        "review_link": "https://www.facebook.com/itzel.olguinromero/posts/2872887549397901",
        "reviewer_picture": "itzel_galleta.jpg",
        "display_date": "19/11/2019"
    },
    {
        "review_text": "✔ Los recomiendo 💯 realmente esta es una gran pagina, estuvieron muy pendientes 🗣  me ayudaron a encontrar a mi tony 🐶 son los mejores, ¡Gracias por todo! 😢😍",
        "review_date": 1573928975,
        "review_display_date": "2019-11-16T18:29:35+0000",
        "review_length": 160,
        "reviewer_name": "Kathe Sanchez",
        "reviewer_country": "Colombia.png",
        "review_link": "https://www.facebook.com/kathe.sanchez.5055/posts/2382346695428123",
        "reviewer_picture": "kathe_tony.jpg",
        "display_date": "16/11/2019"
    },
    {
        "review_text": "Estoy muy agradecida con Clabki, con el profesionalismo que trabajan una causa que prácticamente podría verse como perdida. Me brindaron confianza y puse primeramente en Dios y luego en ellos toda mi fe y mi perrita ya está en casa. Gracias",
        "review_date": 1572484128,
        "review_display_date": "2019-10-31T01:08:48+0000",
        "review_length": 244,
        "reviewer_name": "Sandra Pineda",
        "reviewer_country": "Colombia.png",
        "review_link": "https://www.facebook.com/permalink.php?story_fbid=117922406300040&id=100042468443168",
        "reviewer_picture": "sandra_honey.png",
        "display_date": "30/10/2019"
    },
    {
        "review_text": "Excelente servicio, son muy atentos y prestos a ayudar en un momento tan difícil como es la desaparición de un amigo fiel como lo son nuestras mascotas ¡Gracias! Rocko ya descansa tranquilo en casa 🐶",
        "review_date": 1571714815,
        "review_display_date": "2019-10-22T03:26:55+0000",
        "review_length": 200,
        "reviewer_name": "Mabel Portilla",
        "reviewer_country": "Colombia.png",
        "review_link": "https://www.facebook.com/mabel.portilla/posts/10157725456273205",
        "reviewer_picture": "mabel_rocko.png",
        "display_date": "21/10/2019"
    },
    {
        "review_text": "Excelente servicio! Encontré a mi perro en menos de dos días! Muchas gracias",
        "review_date": 1571278687,
        "review_display_date": "2019-10-17T02:18:07+0000",
        "review_length": 78,
        "reviewer_name": "Jose Pablo Andres",
        "reviewer_country": "Mexico.png",
        "review_link": "https://www.facebook.com/josepablo.andresg/posts/2624434190947371",
        "reviewer_picture": "pablo_mateo.png",
        "display_date": "16/10/2019"
    },
    {
        "review_text": "Es un excelente servicio, lo recomiendo 100%, no es por exagerar pero después de recibir la ayuda de este servicio, mi perro apareció en 5 mins",
        "review_date": 1571261935,
        "review_display_date": "2019-10-16T21:38:55+0000",
        "review_length": 145,
        "reviewer_name": "Miguel Angel Burbano",
        "reviewer_country": "Colombia.png",
        "review_link": "https://www.facebook.com/miguelangle.burbano/posts/3120143344714426",
        "reviewer_picture": "miguel_zeus.jpg",
        "display_date": "16/10/2019"
    },
    {
        "review_text": "Excelente servicio, mi perrito se había perdido hace algunos días, hoy lo encontramos y ya está con nosotros en la casa. De verdad sí recomiendo la app. Buen servicio, espero que todos los que usen encuentren a sus mascotas.♥️♥️♥️🤩",
        "review_date": 1570732718,
        "review_display_date": "2019-10-10T18:38:38+0000",
        "review_length": 232,
        "reviewer_name": "Nicki Zumarraga",
        "reviewer_country": "Ecuador.png",
        "review_link": "https://www.facebook.com/nicki.zumarraga/posts/2466986566720933",
        "reviewer_picture": "nicki_scooby.png",
        "display_date": "10/10/2019"
    },
    {
        "review_text": "Excelente servicio, hoy mi perrita se había perdido, pero la pudimos encontrar y ya está con nosotros en la casa. Recomiendo esta aplicación",
        "review_date": 1569037126,
        "review_display_date": "2019-09-21T03:38:46+0000",
        "review_length": 140,
        "reviewer_name": "Diego Andres Rozo Molina",
        "reviewer_country": "Colombia.png",
        "review_link": "https://www.facebook.com/baterydrum/posts/2990306670984862",
        "reviewer_picture": "diego_lulu.png",
        "display_date": "20/09/2019"
    },
    {
        "review_text": "Excelente servicio, respuesta muy rápida, atención cálida e inmediata, gracias a la publicación apareció mi mascota en 3 días.",
        "review_date": 1568517279,
        "review_display_date": "2019-09-15T03:14:39+0000",
        "review_length": 126,
        "reviewer_name": "Sebastian Ochoa Lopez",
        "reviewer_country": "Colombia.png",
        "review_link": "https://www.facebook.com/sebastian.ochoalopez.1/posts/10157667090099166",
        "reviewer_picture": "sebastian_lupe.jpg",
        "display_date": "14/09/2019"
    },
    {
        "review_text": "Gracias por la ayuda para encontrar a Roco, una familia más está feliz hoy... Gracias totales...",
        "review_date": 1568502490,
        "review_display_date": "2019-09-14T23:08:10+0000",
        "review_length": 94,
        "reviewer_name": "Diana Castro Ovalle",
        "reviewer_country": "Colombia.png",
        "review_link": "https://www.facebook.com/dinachoca/posts/10157020413079215",
        "reviewer_picture": "diana_roco.jpg",
        "display_date": "14/09/2019"
    },
    {
        "review_text": "Bosque apareció anoche a las 9 y media de la noche, ya está con nosotros, gracias a Clabki, hicieron un trabajo espectacular de búsqueda y 24 horas después de haber contactado a Clabki el perro apareció. Estoy muy agradecida, los amo. Clabki gracias de corazón, los amo 🥰🥰🥰🥰😘🤣🤣🤣🤣🤣",
        "review_date": 1567954637,
        "review_display_date": "2019-09-08T14:57:17+0000",
        "review_length": 293,
        "reviewer_name": "Maria Arevalo Benedetti",
        "reviewer_country": "Colombia.png",
        "review_link": "https://www.facebook.com/mabenedetti/posts/10156837289714858",
        "reviewer_picture": "maria_bosque.png",
        "display_date": "08/09/2019"
    },
    {
        "review_text": "Excelente trabajo compañeros, son de muy buena ayuda, hicieron que nuestro perrito que ya llevaba 5 días extraviado apareciera, su publicación fue excelente y por medio de ella fue que apareció nuestro niño, gracias a ustedes clabki nuestro Gerónimo está de regreso en su hogar",
        "review_date": 1567885046,
        "review_display_date": "2019-09-07T19:37:26+0000",
        "review_length": 282,
        "reviewer_name": "Jamir David Salas",
        "reviewer_country": "Colombia.png",
        "review_link": "https://www.facebook.com/juandavid1065/posts/2347244955374526",
        "reviewer_picture": "jamir_geronimo.png",
        "display_date": "07/09/2019"
    },
    {
        "review_text": "Muy recomendable, están muy pendientes de todo y gracias a ellos pudimos encontrar a nuestro perrito 👌😊",
        "review_date": 1567631809,
        "review_display_date": "2019-09-04T21:16:49+0000",
        "review_length": 104,
        "reviewer_name": "Mimi Altahona",
        "reviewer_country": "Colombia.png",
        "review_link": "https://www.facebook.com/milagro.altahona/posts/10205984877778347",
        "reviewer_picture": "mimi_cooper.jpg",
        "display_date": "04/09/2019"
    },
    {
        "review_text": "El servicio me pareció excelente ya que comunicó que nuestra perrita estaba perdida y recibimos muchas respuestas de las personas y gracias a ello pudimos encontrar a nuestra mascota asi que: ¡Gracias clabki!",
        "review_date": 1567549980,
        "review_display_date": "2019-09-03T22:33:00+0000",
        "review_length": 208,
        "reviewer_name": "Francisca Aguiluz",
        "reviewer_country": "Mexico.png",
        "review_link": "https://www.facebook.com/francisca.aguiluz/posts/748580808897179",
        "reviewer_picture": "francisca_aria.jpg",
        "display_date": "03/09/2019"
    },
    {
        "review_text": "Gracias, con su ayuda logramos encontrar a #Nio!",
        "review_date": 1565569289,
        "review_display_date": "2019-08-12T00:21:29+0000",
        "review_length": 49,
        "reviewer_name": "Olga Zarate Aleman",
        "reviewer_country": "Colombia.png",
        "review_link": "https://www.facebook.com/olga.z.aleman/posts/10216789184456002",
        "reviewer_picture": "olga_nio.jpg",
        "display_date": "11/08/2019"
    },
    {
        "review_text": "Encontramos a mi bebé después de una semana del anuncio, ¡muchas gracias!",
        "review_date": 1565066858,
        "review_display_date": "2019-08-06T04:47:38+0000",
        "review_length": 75,
        "reviewer_name": "Yoss U Coree",
        "reviewer_country": "Mexico.png",
        "review_link": "https://www.facebook.com/MstrHuahua117/posts/2557237330986053",
        "reviewer_picture": "yoss_teo.jpg",
        "display_date": "05/08/2019"
    },
    {
        "review_text": "Excelente servicio, gracias por devolvernos a nuestra perrita. Mi hija está muy feliz ¡gracias, gracias!",
        "review_date": 1564070277,
        "review_display_date": "2019-07-25T15:57:57+0000",
        "review_length": 101,
        "reviewer_name": "Nancy Sandoval",
        "reviewer_country": "Ecuador.png",
        "review_link": "https://www.facebook.com/nancy.sandoval.77377/posts/10217355663835405",
        "reviewer_picture": "nancy_laina.jpg",
        "display_date": "25/07/2019"
    },
    {
        "review_text": "Su difusión fue inmediata y llegó  a más personas de las que yo creía en tan poco tiempo. Ayudaron mucho a encontrar a mi mascota. Gracias",
        "review_date": 1563998345,
        "review_display_date": "2019-07-24T19:59:05+0000",
        "review_length": 139,
        "reviewer_name": "Hector Cortes",
        "reviewer_country": "Mexico.png",
        "review_link": "https://www.facebook.com/manuel.sanabria.982845/posts/2202337893389773",
        "reviewer_picture": "hector_pecas.jpg",
        "display_date": "24/07/2019"
    },
    {
        "review_text": "Es una Bendición que exista este servicio, en tan solo 3 horas de hacer la publicación ya Ruzzy había aparecido, super recomendada... Ojalá y pueda ayudar a quienes lo necesitan",
        "review_date": 1563461475,
        "review_display_date": "2019-07-18T14:51:15+0000",
        "review_length": 176,
        "reviewer_name": "Leydi Romero",
        "reviewer_country": "Colombia.png",
        "review_link": "https://www.facebook.com/leydirom/posts/10219696701826844",
        "reviewer_picture": "leydi_ruzzy.jpg",
        "display_date": "18/07/2019"
    }
]